{
    "GameStartCameraMove": {
        "moveTime_0": 1.5,
        "moveTime_1": 1.5,
        "moveTime_2": 1.0,
        "moveTime_3": 1.0,
        "moveTime_4": 1.0,
        "pos_0": [
            0.0,
            30.0,
            -13.0
        ],
        "pos_1": [
            0.0,
            14.0,
            -20.0
        ],
        "pos_2": [
            0.0,
            8.0,
            -30.0
        ],
        "pos_3": [
            0.0,
            15.0,
            -28.0
        ],
        "pos_4": [
            0.0,
            50.0,
            -28.0
        ],
        "rotate_0": [
            55.0,
            0.0,
            0.0
        ],
        "rotate_1": [
            0.0,
            0.0,
            0.0
        ],
        "rotate_2": [
            75.0,
            0.0,
            0.0
        ],
        "rotate_3": [
            0.0,
            0.0,
            0.0
        ],
        "rotate_4": [
            55.0,
            0.0,
            0.0
        ]
    }
}
